main.py
setup.py
ByteMLPerf.egg-info/PKG-INFO
ByteMLPerf.egg-info/SOURCES.txt
ByteMLPerf.egg-info/dependency_links.txt
ByteMLPerf.egg-info/requires.txt
ByteMLPerf.egg-info/top_level.txt